odoo/addons/stock_picking_origin_reference/README.rst
odoo/addons/stock_picking_origin_reference/__init__.py
odoo/addons/stock_picking_origin_reference/__manifest__.py
odoo/addons/stock_picking_origin_reference/i18n/it.po
odoo/addons/stock_picking_origin_reference/i18n/pt.po
odoo/addons/stock_picking_origin_reference/i18n/pt_BR.po
odoo/addons/stock_picking_origin_reference/i18n/stock_picking_origin_reference.pot
odoo/addons/stock_picking_origin_reference/models/__init__.py
odoo/addons/stock_picking_origin_reference/models/stock_picking.py
odoo/addons/stock_picking_origin_reference/readme/CONFIGURE.md
odoo/addons/stock_picking_origin_reference/readme/CONTRIBUTORS.md
odoo/addons/stock_picking_origin_reference/readme/DESCRIPTION.md
odoo/addons/stock_picking_origin_reference/static/description/icon.png
odoo/addons/stock_picking_origin_reference/static/description/index.html
odoo/addons/stock_picking_origin_reference/tests/__init__.py
odoo/addons/stock_picking_origin_reference/tests/test_stock_picking_origin_reference.py
odoo/addons/stock_picking_origin_reference/views/stock_picking_views.xml
odoo_addon_stock_picking_origin_reference-19.0.1.0.0.2.dist-info/METADATA
odoo_addon_stock_picking_origin_reference-19.0.1.0.0.2.dist-info/WHEEL
odoo_addon_stock_picking_origin_reference-19.0.1.0.0.2.dist-info/top_level.txt
odoo_addon_stock_picking_origin_reference-19.0.1.0.0.2.dist-info/RECORD
