Metadata-Version: 2.1
Name: odoo-addon-stock_picking_origin_reference
Version: 19.0.1.0.0.2
Requires-Dist: odoo==19.0.*
Summary: Add clickable button to the Transfer Source Document.
Home-page: https://github.com/OCA/stock-logistics-workflow
License: AGPL-3
Author: ForgeFlow, Odoo Community Association (OCA)
Author-email: support@odoo-community.org
Classifier: Programming Language :: Python
Classifier: Framework :: Odoo
Classifier: Framework :: Odoo :: 19.0
Classifier: License :: OSI Approved :: GNU Affero General Public License v3
